steamstorefront/__init__.py
steamstorefront/app.py
steamstorefront/bundle.py
steamstorefront/cli.py
steamstorefront/errors.py
steamstorefront/misc.py
steamstorefront/package.py
steamstorefront/steamstorefront.py
steamstorefront-0.0.3.8.dist-info/AUTHORS.rst
steamstorefront-0.0.3.8.dist-info/LICENSE
steamstorefront-0.0.3.8.dist-info/METADATA
steamstorefront-0.0.3.8.dist-info/WHEEL
steamstorefront-0.0.3.8.dist-info/top_level.txt
steamstorefront-0.0.3.8.dist-info/RECORD
