Metadata-Version: 2.1
Name: steamstorefront
Version: 0.0.3.8
Summary: Steam Store Front is an easy to use package to get game or app details from steam store.
Home-page: https://github.com/santoshpanna/steamstorefront
Author: Santosh Panna
Author-email: santoshpanna.sp@gmail.com
License: MIT license
Keywords: steamstorefront
Platform: UNKNOWN
Classifier: Development Status :: 2 - Pre-Alpha
Classifier: Intended Audience :: Developers
Classifier: License :: OSI Approved :: MIT License
Classifier: Natural Language :: English
Classifier: Programming Language :: Python :: 3
Classifier: Programming Language :: Python :: 3.5
Classifier: Programming Language :: Python :: 3.6
Classifier: Programming Language :: Python :: 3.7
Classifier: Programming Language :: Python :: 3.8
Requires-Python: >=3.5
Requires-Dist: beautifulsoup4 (>=4.7.0)
Requires-Dist: fuzzywuzzy (>=0.17.0)
Requires-Dist: html5lib (>=1.0.0)
Requires-Dist: python-Levenshtein (>=0.12.0)
Requires-Dist: requests (>=2.21.0)
Requires-Dist: w3lib (>=1.19.0)
